andyao/mdspliter/tree/__init__.py
andyao/mdspliter/tree/node.py
python_pack_for_ci-0.1.0.dist-info/LICENSE
python_pack_for_ci-0.1.0.dist-info/WHEEL
python_pack_for_ci-0.1.0.dist-info/METADATA
python_pack_for_ci-0.1.0.dist-info/RECORD
