Metadata-Version: 2.1
Name: python-pack-for-ci
Version: 0.1.0
Summary: Project for testing.
Author: zen96285
Author-email: zen96285@gmail.com
Requires-Python: >=3.6,<4.0
Classifier: Programming Language :: Python :: 3
Classifier: Programming Language :: Python :: 3.6
Classifier: Programming Language :: Python :: 3.7
Classifier: Programming Language :: Python :: 3.8
Classifier: Programming Language :: Python :: 3.9
